CIBer/CIBer_Engineering.py
CIBer/CIBer_class.py
CIBer/__init__.py
CIBer-0.1.8.dist-info/LICENSE
CIBer-0.1.8.dist-info/METADATA
CIBer-0.1.8.dist-info/WHEEL
CIBer-0.1.8.dist-info/top_level.txt
CIBer-0.1.8.dist-info/RECORD
