Metadata-Version: 2.2
Name: CIBer
Version: 0.1.8
Summary: A Comonotone-Independence Bayesian Classifier
Home-page: https://github.com/ross1456/CIBer-Package.git
Author: Kaiser & Ross
Author-email: rosscooper@link.cuhk.edu.hk
License: MIT
Classifier: Programming Language :: Python :: 3
Classifier: License :: OSI Approved :: MIT License
Classifier: Operating System :: OS Independent
Requires-Python: >=3.7
License-File: LICENSE
Requires-Dist: numpy
Requires-Dist: pandas
Requires-Dist: scipy
Requires-Dist: scikit-learn
Dynamic: author
Dynamic: author-email
Dynamic: classifier
Dynamic: description
Dynamic: description-content-type
Dynamic: home-page
Dynamic: license
Dynamic: requires-dist
Dynamic: requires-python
Dynamic: summary
